[{"geometry": {"type": "Polygon", "coordinates": [[[61, 520.5], [50.5, 525.5], [31.25, 602], [12.25, 671.5], [17.75, 680.75], [287.75, 751], [292, 736.75], [311.75, 742.25], [308, 757.5], [451.75, 793.75], [467, 811], [476.25, 797.75], [517.5, 640.75], [61, 520.5]]]}, "title": "Формула Кино", "id": "1", "floor": 1}, {"geometry": null, "title": "Город детей «Минополис»", "id": "2", "floor": 2}, {"geometry": null, "title": "Ледовый каток", "id": "3", "floor": 3}, {"geometry": {"type": "Polygon", "coordinates": [[[417.25, 455.25], [378.5, 603.25], [517, 640.25], [555, 494.5], [417.25, 455.25]]]}, "title": "OZ One", "id": "4", "floor": 1}, {"geometry": null, "title": "Боулинг", "id": "5", "floor": 2}, {"geometry": null, "title": "Бильярд", "id": "6", "floor": 3}, {"geometry": null, "title": "Караоке Клуб", "id": "7", "floor": 1}, {"geometry": null, "title": "Bebe", "id": "29", "floor": 2}, {"geometry": null, "title": "Bessini", "id": "32", "floor": 3}, {"geometry": null, "title": "COLIN’S", "id": "34", "floor": 1}, {"geometry": null, "title": "Fun Day", "id": "38", "floor": 2}, {"geometry": null, "title": "Lime", "id": "48", "floor": 3}, {"geometry": null, "title": "SELA", "id": "60", "floor": 1}, {"geometry": null, "title": "Vestido", "id": "64", "floor": 2}, {"geometry": null, "title": "D&P Perfumum", "id": "70", "floor": 3}, {"geometry": null, "title": "Айкрафт", "id": "73", "floor": 1}, {"geometry": null, "title": "Giovanni Botticelli", "id": "86", "floor": 2}, {"geometry": null, "title": "SELA", "id": "104", "floor": 3}, {"geometry": null, "title": "Орхидея", "id": "120", "floor": 1}, {"geometry": null, "title": "Cropp", "id": "138", "floor": 2}, {"geometry": null, "title": "H&M", "id": "141", "floor": 3}, {"geometry": null, "title": "Quiksilver", "id": "154", "floor": 1}, {"geometry": null, "title": "SELA", "id": "157", "floor": 2}, {"geometry": null, "title": "Quiksilver", "id": "169", "floor": 3}, {"geometry": null, "title": "SGH Дом солнцезащитных очков", "id": "177", "floor": 1}, {"geometry": null, "title": "Мебельный салон Елена", "id": "199", "floor": 2}, {"geometry": null, "title": "Baby Club", "id": "203", "floor": 3}, {"geometry": null, "title": "ACCENT", "id": "223", "floor": 1}, {"geometry": null, "title": "SGH Дом солнцезащитных очков", "id": "228", "floor": 2}, {"geometry": null, "title": "ЗОЛОТОЙ ЛОТОС", "id": "234", "floor": 3}, {"geometry": null, "title": "Baskin", "id": "239", "floor": 1}, {"geometry": null, "title": "BBQ time", "id": "240", "floor": 2}, {"geometry": null, "title": "Coffee Space", "id": "242", "floor": 3}, {"geometry": null, "title": "FAD BAR", "id": "244", "floor": 1}, {"geometry": null, "title": "ProSushi", "id": "247", "floor": 2}, {"geometry": null, "title": "ЁХА Пицца", "id": "250", "floor": 3}, {"geometry": null, "title": "Коровка из Кореновки", "id": "252", "floor": 1}, {"geometry": null, "title": "Мармарит", "id": "253", "floor": 2}, {"geometry": null, "title": "СУШИВЁСЛА", "id": "254", "floor": 3}, {"geometry": null, "title": "FAD BAR", "id": "257", "floor": 1}, {"geometry": null, "title": "Tanoshy", "id": "258", "floor": 2}, {"geometry": null, "title": "Мармарит", "id": "259", "floor": 3}, {"geometry": null, "title": "Dаs Koлбаs", "id": "262", "floor": 1}, {"geometry": null, "title": "FAD BAR", "id": "263", "floor": 2}, {"geometry": null, "title": "McDonalds", "id": "266", "floor": 3}, {"geometry": null, "title": "ProSushi", "id": "267", "floor": 1}, {"geometry": null, "title": "ЁХА Пицца", "id": "270", "floor": 2}, {"geometry": null, "title": "Коровка из Кореновки", "id": "272", "floor": 3}, {"geometry": null, "title": "Мармарит", "id": "273", "floor": 1}, {"geometry": null, "title": "СУШИВЁСЛА", "id": "274", "floor": 2}, {"geometry": null, "title": "BBQ time", "id": "277", "floor": 3}, {"geometry": null, "title": "Coffee Space", "id": "279", "floor": 1}, {"geometry": null, "title": "Coffeeshop Company", "id": "280", "floor": 2}, {"geometry": null, "title": "FAD BAR", "id": "281", "floor": 3}, {"geometry": null, "title": "Блинберри", "id": "284", "floor": 1}, {"geometry": null, "title": "Коровка из Кореновки", "id": "288", "floor": 2}, {"geometry": null, "title": "Мармарит", "id": "289", "floor": 3}, {"geometry": null, "title": "Circle Boutique", "id": "307", "floor": 1}, {"geometry": null, "title": "Colin's", "id": "308", "floor": 2}, {"geometry": null, "title": "Cropp Town", "id": "309", "floor": 3}, {"geometry": null, "title": "JS Selected", "id": "312", "floor": 1}, {"geometry": null, "title": "Kiabi", "id": "313", "floor": 2}, {"geometry": null, "title": "KOTON", "id": "314", "floor": 3}, {"geometry": null, "title": "Lacoste", "id": "315", "floor": 1}, {"geometry": null, "title": "LC Waikiki", "id": "316", "floor": 2}, {"geometry": null, "title": "Levi's", "id": "317", "floor": 3}, {"geometry": null, "title": "Mango", "id": "318", "floor": 1}, {"geometry": null, "title": "Massimo Dutti", "id": "319", "floor": 2}, {"geometry": null, "title": "Modis", "id": "320", "floor": 3}, {"geometry": null, "title": "O'stin", "id": "321", "floor": 1}, {"geometry": null, "title": "Pull&Bear", "id": "322", "floor": 2}, {"geometry": null, "title": "SELA", "id": "323", "floor": 3}, {"geometry": null, "title": "Takko Fashion", "id": "324", "floor": 1}, {"geometry": null, "title": "Finn Flare", "id": "325", "floor": 2}, {"geometry": null, "title": "Terranova", "id": "326", "floor": 3}, {"geometry": null, "title": "U.S. Polo Assn.", "id": "327", "floor": 1}, {"geometry": null, "title": "Zolla", "id": "328", "floor": 2}, {"geometry": null, "title": "Снежная Королева", "id": "329", "floor": 3}, {"geometry": null, "title": "House", "id": "330", "floor": 1}, {"geometry": null, "title": "Reserved", "id": "331", "floor": 2}, {"geometry": null, "title": "Shaman", "id": "332", "floor": 3}, {"geometry": null, "title": "Westland", "id": "333", "floor": 1}, {"geometry": null, "title": "BGN", "id": "334", "floor": 2}, {"geometry": null, "title": "Concept Club", "id": "335", "floor": 3}, {"geometry": null, "title": "Kira Plastinina", "id": "336", "floor": 1}, {"geometry": null, "title": "Stradivarius", "id": "337", "floor": 2}, {"geometry": null, "title": "Waggon", "id": "338", "floor": 3}, {"geometry": null, "title": "Zara", "id": "339", "floor": 1}, {"geometry": null, "title": "Zarina", "id": "340", "floor": 2}, {"geometry": null, "title": "Aventure", "id": "341", "floor": 3}, {"geometry": null, "title": "BeFree", "id": "342", "floor": 1}, {"geometry": null, "title": "Noche Mio", "id": "343", "floor": 2}, {"geometry": null, "title": "DS Studio", "id": "344", "floor": 3}, {"geometry": null, "title": "Incity", "id": "345", "floor": 1}, {"geometry": null, "title": "Love Republic", "id": "346", "floor": 2}, {"geometry": null, "title": "Mohito", "id": "347", "floor": 3}, {"geometry": null, "title": "Olivero Detti", "id": "348", "floor": 1}, {"geometry": null, "title": "Буду мамой", "id": "349", "floor": 2}, {"geometry": null, "title": "Cacharel", "id": "350", "floor": 3}, {"geometry": null, "title": "Giovanni Botichelli", "id": "351", "floor": 1}, {"geometry": null, "title": "Henderson", "id": "352", "floor": 2}, {"geometry": null, "title": "Kanzler", "id": "353", "floor": 3}, {"geometry": null, "title": "Paul Becker", "id": "354", "floor": 1}, {"geometry": null, "title": "Pierre Cardin", "id": "355", "floor": 2}, {"geometry": null, "title": "Zara Man", "id": "356", "floor": 3}, {"geometry": null, "title": "Rich Man", "id": "357", "floor": 1}, {"geometry": null, "title": "Zara Kids", "id": "358", "floor": 2}, {"geometry": null, "title": "Acoola", "id": "359", "floor": 3}, {"geometry": null, "title": "Adidas Kids", "id": "360", "floor": 1}, {"geometry": null, "title": "Crockid", "id": "361", "floor": 2}, {"geometry": null, "title": "Danilo", "id": "362", "floor": 3}, {"geometry": null, "title": "Imaginarium", "id": "363", "floor": 1}, {"geometry": null, "title": "LEGO", "id": "364", "floor": 2}, {"geometry": null, "title": "SHAGOVITA", "id": "365", "floor": 3}, {"geometry": null, "title": "Буду мамой", "id": "366", "floor": 1}, {"geometry": null, "title": "Детский мир", "id": "367", "floor": 2}, {"geometry": null, "title": "Дочки", "id": "368", "floor": 3}, {"geometry": null, "title": "Катюша", "id": "369", "floor": 1}, {"geometry": null, "title": "Оранжевый Слон", "id": "370", "floor": 2}, {"geometry": null, "title": "О'КЕЙ", "id": "371", "floor": 3}, {"geometry": null, "title": "PODIUM market", "id": "372", "floor": 1}, {"geometry": null, "title": "Proffline", "id": "373", "floor": 2}, {"geometry": null, "title": "L'OCCITANE", "id": "374", "floor": 3}, {"geometry": null, "title": "Lulu Paris", "id": "376", "floor": 1}, {"geometry": null, "title": "Yves Rocher", "id": "377", "floor": 2}, {"geometry": null, "title": "Л'Этуаль", "id": "378", "floor": 3}, {"geometry": null, "title": "Аптека Радуга", "id": "379", "floor": 1}, {"geometry": null, "title": "Айкрафт Оптика", "id": "380", "floor": 2}, {"geometry": null, "title": "РИВ ГОШ", "id": "381", "floor": 3}, {"geometry": null, "title": "Цирюльник", "id": "382", "floor": 1}, {"geometry": null, "title": "Calzedonia", "id": "383", "floor": 2}, {"geometry": null, "title": "Intimissimi", "id": "384", "floor": 3}, {"geometry": null, "title": "Oysho", "id": "385", "floor": 1}, {"geometry": null, "title": "Tezenis", "id": "386", "floor": 2}, {"geometry": null, "title": "ORCHIDEJA", "id": "387", "floor": 3}, {"geometry": null, "title": "Anabel Arto", "id": "388", "floor": 1}, {"geometry": null, "title": "Atlantic", "id": "389", "floor": 2}, {"geometry": null, "title": "Prisco", "id": "390", "floor": 3}, {"geometry": null, "title": "3", "id": "391", "floor": 1}, {"geometry": null, "title": "Casio", "id": "392", "floor": 2}, {"geometry": null, "title": "Parfois", "id": "393", "floor": 3}, {"geometry": null, "title": "Pandora", "id": "394", "floor": 1}, {"geometry": null, "title": "Persian", "id": "395", "floor": 2}, {"geometry": null, "title": "Sunlight", "id": "396", "floor": 3}, {"geometry": null, "title": "Sunglass Hut", "id": "397", "floor": 1}, {"geometry": null, "title": "Time Square", "id": "398", "floor": 2}, {"geometry": null, "title": "Валдай", "id": "399", "floor": 3}, {"geometry": null, "title": "Времечко", "id": "400", "floor": 1}, {"geometry": null, "title": "Гранатовый Браслет", "id": "401", "floor": 2}, {"geometry": null, "title": "Золотой Ларец", "id": "402", "floor": 3}, {"geometry": null, "title": "Золотой Лотос", "id": "403", "floor": 1}, {"geometry": null, "title": "Магия золота", "id": "405", "floor": 2}, {"geometry": null, "title": "Ростзолото", "id": "406", "floor": 3}, {"geometry": null, "title": "Серебряный слон", "id": "407", "floor": 1}, {"geometry": null, "title": "Ювелир Дизайн", "id": "408", "floor": 2}, {"geometry": null, "title": "Adidas", "id": "409", "floor": 3}, {"geometry": null, "title": "Adidas Neo", "id": "410", "floor": 1}, {"geometry": null, "title": "Adidas Originals", "id": "411", "floor": 2}, {"geometry": null, "title": "Puma", "id": "412", "floor": 3}, {"geometry": null, "title": "Quicksilver", "id": "413", "floor": 1}, {"geometry": null, "title": "Reebok", "id": "414", "floor": 2}, {"geometry": null, "title": "Декатлон", "id": "415", "floor": 3}, {"geometry": null, "title": "Спортмастер", "id": "416", "floor": 1}, {"geometry": null, "title": "Alba", "id": "417", "floor": 2}, {"geometry": null, "title": "Antonio Biaggi", "id": "418", "floor": 3}, {"geometry": null, "title": "Belwest", "id": "419", "floor": 1}, {"geometry": null, "title": "Carlo Pazolini", "id": "420", "floor": 2}, {"geometry": null, "title": "Etaloni", "id": "421", "floor": 3}, {"geometry": null, "title": "KARI", "id": "422", "floor": 1}, {"geometry": null, "title": "Mario Mikke", "id": "423", "floor": 2}, {"geometry": null, "title": "Monsorro", "id": "424", "floor": 3}, {"geometry": null, "title": "No One", "id": "425", "floor": 1}, {"geometry": null, "title": "Paolo Conte", "id": "426", "floor": 2}, {"geometry": null, "title": "Rendez", "id": "427", "floor": 3}, {"geometry": null, "title": "Rieker", "id": "428", "floor": 1}, {"geometry": null, "title": "Respect", "id": "429", "floor": 2}, {"geometry": null, "title": "Tamaris", "id": "430", "floor": 3}, {"geometry": null, "title": "TJ Collection", "id": "431", "floor": 1}, {"geometry": null, "title": "Zenden", "id": "432", "floor": 2}, {"geometry": null, "title": "Пан Чемодан", "id": "433", "floor": 3}, {"geometry": null, "title": "Центр обувь", "id": "434", "floor": 1}, {"geometry": null, "title": "Baggage", "id": "435", "floor": 2}, {"geometry": null, "title": "ECCO", "id": "436", "floor": 3}, {"geometry": null, "title": "Aura of Bogemia", "id": "437", "floor": 1}, {"geometry": null, "title": "Gipfel", "id": "438", "floor": 2}, {"geometry": null, "title": "Hoff", "id": "439", "floor": 3}, {"geometry": null, "title": "OBI", "id": "440", "floor": 1}, {"geometry": null, "title": "Togas", "id": "441", "floor": 2}, {"geometry": null, "title": "Williams Et Oliver", "id": "442", "floor": 3}, {"geometry": null, "title": "Zara Home", "id": "443", "floor": 1}, {"geometry": null, "title": "Арт", "id": "444", "floor": 2}, {"geometry": null, "title": "Ap Home", "id": "445", "floor": 3}, {"geometry": null, "title": "Askona", "id": "446", "floor": 1}, {"geometry": null, "title": "Desondo", "id": "448", "floor": 2}, {"geometry": null, "title": "Fandeco", "id": "449", "floor": 3}, {"geometry": null, "title": "Kare", "id": "450", "floor": 1}, {"geometry": null, "title": "Kitchen Cool", "id": "451", "floor": 2}, {"geometry": null, "title": "Зеленый Попугай", "id": "452", "floor": 3}, {"geometry": null, "title": "МАРТ", "id": "453", "floor": 1}, {"geometry": null, "title": "Мебель от Горелова", "id": "454", "floor": 2}, {"geometry": null, "title": "Салон мебели \"Елена\"", "id": "455", "floor": 3}, {"geometry": null, "title": "Уютерра", "id": "456", "floor": 1}, {"geometry": null, "title": "DIXIS", "id": "457", "floor": 2}, {"geometry": null, "title": "Imarket", "id": "458", "floor": 3}, {"geometry": null, "title": "iБутик", "id": "459", "floor": 1}, {"geometry": null, "title": "I", "id": "460", "floor": 2}, {"geometry": null, "title": "JoyeShop", "id": "461", "floor": 3}, {"geometry": null, "title": "Samsung", "id": "462", "floor": 1}, {"geometry": null, "title": "Tele 2", "id": "463", "floor": 2}, {"geometry": null, "title": "Yota", "id": "464", "floor": 3}, {"geometry": null, "title": "Евросеть", "id": "465", "floor": 1}, {"geometry": null, "title": "Мегафон", "id": "466", "floor": 2}, {"geometry": null, "title": "МТС", "id": "467", "floor": 3}, {"geometry": null, "title": "Телефон.ру", "id": "468", "floor": 1}, {"geometry": null, "title": "DNS", "id": "469", "floor": 2}, {"geometry": null, "title": "re:Store", "id": "470", "floor": 3}, {"geometry": null, "title": "Атриум", "id": "471", "floor": 1}, {"geometry": null, "title": "М.Видео", "id": "472", "floor": 2}, {"geometry": null, "title": "ЭСКО", "id": "473", "floor": 3}, {"geometry": null, "title": "Aura of Bohemia", "id": "474", "floor": 1}, {"geometry": null, "title": "Postulat", "id": "475", "floor": 2}, {"geometry": null, "title": "Клумба", "id": "476", "floor": 3}, {"geometry": null, "title": "Три желания", "id": "477", "floor": 1}, {"geometry": null, "title": "Атриум", "id": "478", "floor": 2}, {"geometry": null, "title": "Кофейная кантата", "id": "479", "floor": 3}, {"geometry": null, "title": "Экспедиция", "id": "480", "floor": 1}, {"geometry": null, "title": "DM", "id": "481", "floor": 2}, {"geometry": null, "title": "Грязи.net", "id": "482", "floor": 3}, {"geometry": null, "title": "Лена Ленина", "id": "483", "floor": 1}, {"geometry": null, "title": "ПОЧТА РОССИИ", "id": "484", "floor": 2}, {"geometry": null, "title": "Темп Авто", "id": "485", "floor": 3}, {"geometry": null, "title": "Экспресс Ателье", "id": "486", "floor": 1}, {"geometry": null, "title": "Карамелька", "id": "487", "floor": 2}, {"geometry": null, "title": "Animal Club", "id": "488", "floor": 3}, {"geometry": null, "title": "Zveruga", "id": "489", "floor": 1}, {"geometry": null, "title": "Burger King", "id": "490", "floor": 2}, {"geometry": null, "title": "KFC", "id": "491", "floor": 3}, {"geometry": null, "title": "Livan House", "id": "492", "floor": 1}, {"geometry": null, "title": "Mc Donald's", "id": "493", "floor": 2}, {"geometry": null, "title": "Prima Vera", "id": "494", "floor": 3}, {"geometry": null, "title": "Subway", "id": "495", "floor": 1}, {"geometry": null, "title": "БлинБерри/Сушивёсла", "id": "496", "floor": 2}, {"geometry": null, "title": "Гирос", "id": "497", "floor": 3}, {"geometry": null, "title": "Голый повар", "id": "498", "floor": 1}, {"geometry": null, "title": "Жар Пицца", "id": "499", "floor": 2}, {"geometry": null, "title": "Ташир Пицца", "id": "500", "floor": 3}, {"geometry": null, "title": "Теремок", "id": "501", "floor": 1}, {"geometry": null, "title": "De Marco", "id": "502", "floor": 2}, {"geometry": null, "title": "Origami", "id": "503", "floor": 3}, {"geometry": null, "title": "Голый повар", "id": "504", "floor": 1}, {"geometry": null, "title": "FadBar", "id": "505", "floor": 2}, {"geometry": null, "title": "Ледовый каток SKY ICE", "id": "506", "floor": 3}, {"geometry": null, "title": "Avatar 7D", "id": "507", "floor": 1}, {"geometry": null, "title": "Baby Club", "id": "508", "floor": 2}, {"geometry": null, "title": "Батутный парк \"Маугли\"", "id": "509", "floor": 3}, {"geometry": null, "title": "Карамелька", "id": "510", "floor": 1}, {"geometry": null, "title": "Сокровища Пирата", "id": "511", "floor": 2}, {"geometry": null, "title": "Страна Великания", "id": "512", "floor": 3}, {"geometry": null, "title": "Фан", "id": "513", "floor": 1}, {"geometry": null, "title": "OZ Боулинг/VIP Боулинг", "id": "514", "floor": 2}, {"geometry": null, "title": "OZ Караоке", "id": "515", "floor": 3}, {"geometry": null, "title": "OZ Бильярд", "id": "516", "floor": 1}, {"geometry": null, "title": "Минополис", "id": "517", "floor": 2}, {"geometry": null, "title": "Формула Кино", "id": "518", "floor": 3}, {"geometry": null, "title": "Coffeeshop company", "id": "519", "floor": 1}, {"geometry": null, "title": "100% сок", "id": "520", "floor": 2}, {"geometry": null, "title": "БлинБерри/Сушивёсла", "id": "521", "floor": 3}, {"geometry": null, "title": "Мясная ферма", "id": "522", "floor": 1}, {"geometry": null, "title": "Baskin Robbins", "id": "523", "floor": 2}, {"geometry": null, "title": "Коровка из Кореновки", "id": "524", "floor": 3}, {"geometry": null, "title": "Космик латте", "id": "525", "floor": 1}]